ads2inspire/__init__.py
ads2inspire/cli.py
ads2inspire-0.3.1.dist-info/LICENSE
ads2inspire-0.3.1.dist-info/METADATA
ads2inspire-0.3.1.dist-info/WHEEL
ads2inspire-0.3.1.dist-info/entry_points.txt
ads2inspire-0.3.1.dist-info/top_level.txt
ads2inspire-0.3.1.dist-info/RECORD
