Metadata-Version: 2.1
Name: ads2inspire
Version: 0.3.1
Summary: Replace ADS citations with the appropriate INSPIRE ones in latex and bibtex
Home-page: https://github.com/duetosymmetry/ads2inspire
Author: Leo C. Stein
Author-email: leo.stein@gmail.com
License: MIT
Project-URL: Source, https://github.com/duetosymmetry/ads2inspire
Project-URL: Tracker, https://github.com/duetosymmetry/ads2inspire/issues
Keywords: latex bibtex bibliography
Platform: UNKNOWN
Classifier: Development Status :: 4 - Beta
Classifier: License :: OSI Approved :: MIT License
Classifier: Intended Audience :: Science/Research
Classifier: Topic :: Scientific/Engineering
Classifier: Topic :: Text Processing
Classifier: Topic :: Text Processing :: Markup
Classifier: Topic :: Text Processing :: Markup :: LaTeX
Classifier: Programming Language :: Python :: 3
Classifier: Programming Language :: Python :: 3.6
Classifier: Programming Language :: Python :: 3.7
Classifier: Programming Language :: Python :: 3.8
Requires-Python: >=3.6
Requires-Dist: bibtexparser
Requires-Dist: click (>=6.0)
Provides-Extra: complete
Requires-Dist: black ; extra == 'complete'
Requires-Dist: bumpversion ; extra == 'complete'
Requires-Dist: check-manifest ; extra == 'complete'
Requires-Dist: flake8 ; extra == 'complete'
Requires-Dist: pre-commit ; extra == 'complete'
Requires-Dist: pydocstyle ; extra == 'complete'
Requires-Dist: pytest ; extra == 'complete'
Requires-Dist: pytest-cov (>=2.5.1) ; extra == 'complete'
Requires-Dist: twine ; extra == 'complete'
Provides-Extra: develop
Requires-Dist: black ; extra == 'develop'
Requires-Dist: bumpversion ; extra == 'develop'
Requires-Dist: check-manifest ; extra == 'develop'
Requires-Dist: flake8 ; extra == 'develop'
Requires-Dist: pre-commit ; extra == 'develop'
Requires-Dist: pydocstyle ; extra == 'develop'
Requires-Dist: pytest ; extra == 'develop'
Requires-Dist: pytest-cov (>=2.5.1) ; extra == 'develop'
Requires-Dist: twine ; extra == 'develop'
Provides-Extra: test
Requires-Dist: pytest ; extra == 'test'
Requires-Dist: pytest-cov (>=2.5.1) ; extra == 'test'
Requires-Dist: pydocstyle ; extra == 'test'
Requires-Dist: check-manifest ; extra == 'test'
Requires-Dist: flake8 ; extra == 'test'
Requires-Dist: black ; extra == 'test'
